ffmpeg_for_python/__config__.py
ffmpeg_for_python/__init__.py
ffmpeg_for_python/__utils.py
ffmpeg_for_python/__version__.py
ffmpeg_for_python/exeptions.py
ffmpeg_for_python/ffmpeg.py
ffmpeg_for_python/ffmpeg-bin/readme.md
ffmpeg_for_python-0.3.8.dist-info/METADATA
ffmpeg_for_python-0.3.8.dist-info/WHEEL
ffmpeg_for_python-0.3.8.dist-info/top_level.txt
ffmpeg_for_python-0.3.8.dist-info/RECORD
