Metadata-Version: 2.2
Name: ffmpeg-for-python
Version: 0.3.8
Summary: Wrapper para o binário FFmpeg
Author: PauloCesar-dev404
Author-email: paulocesar0073dev404@gmail.com
License: MIT
Project-URL: Código Fonte, https://raw.githubusercontent.com/PauloCesar-dev404/ffmpeg-for-python/main/ffmpeg_for_python-0.3.8.tar.gz
Project-URL: lib, https://raw.githubusercontent.com/PauloCesar-dev404/ffmpeg-for-python/main/ffmpeg_for_python-0.3.8-py3-none-any.whl
Project-URL: GitHub, https://github.com/PauloCesar-dev404/ffmpeg-for-python
Project-URL: Bugs/Melhorias, https://github.com/PauloCesar-dev404/ffmpeg-for-python/issues
Project-URL: Documentação, https://github.com/PauloCesar-dev404/ffmpeg-for-python/wiki
Keywords: ffmpeg
Platform: any
Requires: requests
Dynamic: author
Dynamic: author-email
Dynamic: description
Dynamic: description-content-type
Dynamic: keywords
Dynamic: license
Dynamic: platform
Dynamic: project-url
Dynamic: requires
Dynamic: summary
